[ { "prim": "parameter",
    "args":
      [ { "prim": "or",
          "args":
            [ { "prim": "nat", "annots": [ "%requestEvent" ] },
              { "prim": "pair",
                "args":
                  [ { "prim": "string", "annots": [ "%name" ] },
                    { "prim": "string", "annots": [ "%videogame" ] },
                    { "prim": "timestamp", "annots": [ "%begin_at" ] },
                    { "prim": "timestamp", "annots": [ "%end_at" ] },
                    { "prim": "timestamp", "annots": [ "%modified_at" ] },
                    { "prim": "pair",
                      "args":
                        [ { "prim": "string", "annots": [ "%team_one" ] },
                          { "prim": "string", "annots": [ "%team_two" ] } ],
                      "annots": [ "%opponents" ] },
                    { "prim": "bool", "annots": [ "%is_finalized" ] },
                    { "prim": "option", "args": [ { "prim": "bool" } ],
                      "annots": [ "%is_draw" ] },
                    { "prim": "option", "args": [ { "prim": "bool" } ],
                      "annots": [ "%is_team_one_win" ] },
                    { "prim": "timestamp", "annots": [ "%start_bet_time" ] },
                    { "prim": "timestamp", "annots": [ "%closed_bet_time" ] },
                    { "prim": "map",
                      "args": [ { "prim": "address" }, { "prim": "mutez" } ],
                      "annots": [ "%bets_team_one" ] },
                    { "prim": "nat", "annots": [ "%bets_team_one_index" ] },
                    { "prim": "mutez", "annots": [ "%bets_team_one_total" ] },
                    { "prim": "map",
                      "args": [ { "prim": "address" }, { "prim": "mutez" } ],
                      "annots": [ "%bets_team_two" ] },
                    { "prim": "nat", "annots": [ "%bets_team_two_index" ] },
                    { "prim": "mutez", "annots": [ "%bets_team_two_total" ] } ],
                "annots": [ "%saveEvent" ] } ] } ] },
  { "prim": "storage",
    "args":
      [ { "prim": "pair",
          "args":
            [ { "prim": "string", "annots": [ "%name" ] },
              { "prim": "string", "annots": [ "%videogame" ] },
              { "prim": "timestamp", "annots": [ "%begin_at" ] },
              { "prim": "timestamp", "annots": [ "%end_at" ] },
              { "prim": "timestamp", "annots": [ "%modified_at" ] },
              { "prim": "pair",
                "args":
                  [ { "prim": "string", "annots": [ "%team_one" ] },
                    { "prim": "string", "annots": [ "%team_two" ] } ],
                "annots": [ "%opponents" ] },
              { "prim": "bool", "annots": [ "%is_finalized" ] },
              { "prim": "option", "args": [ { "prim": "bool" } ],
                "annots": [ "%is_draw" ] },
              { "prim": "option", "args": [ { "prim": "bool" } ],
                "annots": [ "%is_team_one_win" ] },
              { "prim": "timestamp", "annots": [ "%start_bet_time" ] },
              { "prim": "timestamp", "annots": [ "%closed_bet_time" ] },
              { "prim": "map",
                "args": [ { "prim": "address" }, { "prim": "mutez" } ],
                "annots": [ "%bets_team_one" ] },
              { "prim": "nat", "annots": [ "%bets_team_one_index" ] },
              { "prim": "mutez", "annots": [ "%bets_team_one_total" ] },
              { "prim": "map",
                "args": [ { "prim": "address" }, { "prim": "mutez" } ],
                "annots": [ "%bets_team_two" ] },
              { "prim": "nat", "annots": [ "%bets_team_two_index" ] },
              { "prim": "mutez", "annots": [ "%bets_team_two_total" ] },
              { "prim": "map",
                "args": [ { "prim": "string" }, { "prim": "bytes" } ],
                "annots": [ "%metadata" ] },
              { "prim": "address", "annots": [ "%bettingAddr" ] } ] } ] },
  { "prim": "code",
    "args":
      [ [ { "prim": "UNPAIR" },
          { "prim": "IF_LEFT",
            "args":
              [ [ { "prim": "SELF_ADDRESS" }, { "prim": "SWAP" },
                  { "prim": "PAIR" },
                  { "prim": "DUP", "args": [ { "int": "2" } ] },
                  { "prim": "GET", "args": [ { "int": "36" } ] },
                  { "prim": "CONTRACT",
                    "args":
                      [ { "prim": "pair",
                          "args":
                            [ { "prim": "nat",
                                "annots": [ "%requested_event_id" ] },
                              { "prim": "address",
                                "annots": [ "%callback" ] } ] } ],
                    "annots": [ "%getEvent" ] },
                  { "prim": "IF_NONE",
                    "args":
                      [ [ { "prim": "PUSH",
                            "args":
                              [ { "prim": "string" },
                                { "string": "Unknown entrypoint GetEvent" } ] },
                          { "prim": "FAILWITH" } ], [] ] },
                  { "prim": "PUSH",
                    "args": [ { "prim": "mutez" }, { "int": "0" } ] },
                  { "prim": "DIG", "args": [ { "int": "2" } ] },
                  { "prim": "TRANSFER_TOKENS" }, { "prim": "SWAP" },
                  { "prim": "NIL", "args": [ { "prim": "operation" } ] },
                  { "prim": "DIG", "args": [ { "int": "2" } ] },
                  { "prim": "CONS" } ],
                [ { "prim": "SWAP" },
                  { "prim": "DUP", "args": [ { "int": "2" } ] },
                  { "prim": "CAR" },
                  { "prim": "UPDATE", "args": [ { "int": "1" } ] },
                  { "prim": "DUP", "args": [ { "int": "2" } ] },
                  { "prim": "GET", "args": [ { "int": "3" } ] },
                  { "prim": "UPDATE", "args": [ { "int": "3" } ] },
                  { "prim": "DUP", "args": [ { "int": "2" } ] },
                  { "prim": "GET", "args": [ { "int": "5" } ] },
                  { "prim": "UPDATE", "args": [ { "int": "5" } ] },
                  { "prim": "DUP", "args": [ { "int": "2" } ] },
                  { "prim": "GET", "args": [ { "int": "7" } ] },
                  { "prim": "UPDATE", "args": [ { "int": "7" } ] },
                  { "prim": "DUP", "args": [ { "int": "2" } ] },
                  { "prim": "GET", "args": [ { "int": "9" } ] },
                  { "prim": "UPDATE", "args": [ { "int": "9" } ] },
                  { "prim": "DUP", "args": [ { "int": "2" } ] },
                  { "prim": "GET", "args": [ { "int": "11" } ] },
                  { "prim": "UPDATE", "args": [ { "int": "11" } ] },
                  { "prim": "DUP", "args": [ { "int": "2" } ] },
                  { "prim": "GET", "args": [ { "int": "13" } ] },
                  { "prim": "UPDATE", "args": [ { "int": "13" } ] },
                  { "prim": "DUP", "args": [ { "int": "2" } ] },
                  { "prim": "GET", "args": [ { "int": "15" } ] },
                  { "prim": "UPDATE", "args": [ { "int": "15" } ] },
                  { "prim": "DUP", "args": [ { "int": "2" } ] },
                  { "prim": "GET", "args": [ { "int": "17" } ] },
                  { "prim": "UPDATE", "args": [ { "int": "17" } ] },
                  { "prim": "DUP", "args": [ { "int": "2" } ] },
                  { "prim": "GET", "args": [ { "int": "19" } ] },
                  { "prim": "UPDATE", "args": [ { "int": "19" } ] },
                  { "prim": "DUP", "args": [ { "int": "2" } ] },
                  { "prim": "GET", "args": [ { "int": "21" } ] },
                  { "prim": "UPDATE", "args": [ { "int": "21" } ] },
                  { "prim": "DUP", "args": [ { "int": "2" } ] },
                  { "prim": "GET", "args": [ { "int": "23" } ] },
                  { "prim": "UPDATE", "args": [ { "int": "23" } ] },
                  { "prim": "DUP", "args": [ { "int": "2" } ] },
                  { "prim": "GET", "args": [ { "int": "25" } ] },
                  { "prim": "UPDATE", "args": [ { "int": "25" } ] },
                  { "prim": "DUP", "args": [ { "int": "2" } ] },
                  { "prim": "GET", "args": [ { "int": "27" } ] },
                  { "prim": "UPDATE", "args": [ { "int": "27" } ] },
                  { "prim": "DUP", "args": [ { "int": "2" } ] },
                  { "prim": "GET", "args": [ { "int": "29" } ] },
                  { "prim": "UPDATE", "args": [ { "int": "29" } ] },
                  { "prim": "DUP", "args": [ { "int": "2" } ] },
                  { "prim": "GET", "args": [ { "int": "31" } ] },
                  { "prim": "UPDATE", "args": [ { "int": "31" } ] },
                  { "prim": "SWAP" },
                  { "prim": "GET", "args": [ { "int": "32" } ] },
                  { "prim": "UPDATE", "args": [ { "int": "33" } ] },
                  { "prim": "NIL", "args": [ { "prim": "operation" } ] } ] ] },
          { "prim": "PAIR" } ] ] } ]

